setup.py
pystplot/__init__.py
pystplot/html_page.py
pystplot/html_writer.py
pystplot/jstemplate.py
pystplot/plot_api_templates.py
pystplot/pystplot.py
pystplot.egg-info/PKG-INFO
pystplot.egg-info/SOURCES.txt
pystplot.egg-info/dependency_links.txt
pystplot.egg-info/not-zip-safe
pystplot.egg-info/top_level.txt