Metadata-Version: 1.0
Name: pystplot
Version: 0.1.1
Summary: Browser based plotting in python
Home-page: http://github.com/gsterner/sternplot-python
Author: Gustaf Sterner
Author-email: gsterner@gmail.com
License: MIT
Platform: UNKNOWN
